scrapbook/__init__.py
scrapbook/api.py
scrapbook/encoders.py
scrapbook/exceptions.py
scrapbook/log.py
scrapbook/models.py
scrapbook/schemas.py
scrapbook/scraps.py
scrapbook/utils.py
scrapbook/version.py
scrapbook/schemas/scrap.v1.json
scrapbook/tests/__init__.py
scrapbook/tests/test_api.py
scrapbook/tests/test_encoders.py
scrapbook/tests/test_notebooks.py
scrapbook/tests/test_scrapbooks.py
scrapbook/tests/test_scraps.py
scrapbook/tests/test_utils.py
scrapbook/tests/fixtures/tiny.png
scrapbook/tests/notebooks/record.ipynb
scrapbook/tests/notebooks/result_no_exec.ipynb
scrapbook/tests/notebooks/collection/result1.ipynb
scrapbook/tests/notebooks/collection/result2.ipynb
scrapbook-0.5.0.dist-info/LICENSE
scrapbook-0.5.0.dist-info/METADATA
scrapbook-0.5.0.dist-info/WHEEL
scrapbook-0.5.0.dist-info/top_level.txt
scrapbook-0.5.0.dist-info/RECORD
