Metadata-Version: 2.1
Name: scrapbook
Version: 0.5.0
Summary: A library for recording and reading data in Jupyter and nteract Notebooks
Home-page: https://github.com/nteract/scrapbook
Author: nteract contributors
Author-email: nteract@googlegroups.com
License: BSD
Project-URL: Documentation, https://nteract-scrapbook.readthedocs.io
Project-URL: Funding, https://nteract.io
Project-URL: Source, https://github.com/nteract/scrapbook/
Project-URL: Tracker, https://github.com/nteract/scrapbook/issues
Keywords: jupyter,mapreduce,nteract,pipeline,notebook
Platform: UNKNOWN
Classifier: Intended Audience :: Developers
Classifier: Intended Audience :: System Administrators
Classifier: Intended Audience :: Science/Research
Classifier: License :: OSI Approved :: BSD License
Classifier: Programming Language :: Python
Classifier: Programming Language :: Python :: 3
Classifier: Programming Language :: Python :: 3.5
Classifier: Programming Language :: Python :: 3.6
Classifier: Programming Language :: Python :: 3.7
Classifier: Programming Language :: Python :: 3.8
Requires-Python: >=3.5
Provides-Extra: test
Provides-Extra: dev
Provides-Extra: all
Provides-Extra: s3
Provides-Extra: azure
Provides-Extra: gcs
